prpg/__init__.py
prpg/__main__.py
prpg/clipboard.py
prpg/core.py
prpg/rot13.py
prpg/saltfiles.py
prpg/cli/__init__.py
prpg/cli/askpass.py
prpg/cli/common_args.py
prpg/cli/compute.py
prpg/cli/persistent_recall.py
prpg/cli/recall.py
prpg/cli/salts/__init__.py
prpg/cli/salts/add.py
prpg/cli/salts/delete.py
prpg/cli/salts/get.py
prpg/cli/salts/update.py
prpg-0.4.1.dist-info/DESCRIPTION.rst
prpg-0.4.1.dist-info/METADATA
prpg-0.4.1.dist-info/RECORD
prpg-0.4.1.dist-info/WHEEL
prpg-0.4.1.dist-info/entry_points.txt
prpg-0.4.1.dist-info/metadata.json
prpg-0.4.1.dist-info/top_level.txt
