Metadata-Version: 2.0
Name: prpg
Version: 0.4.1
Summary: A pseudorandom password generator / password manager.
Home-page: https://github.com/speezepearson/prpg
Author: speezepearson
Author-email: speeze.pearson+prpg@gmail.com
License: UNKNOWN
Keywords: password password-management password-generation
Platform: UNKNOWN
Classifier: Development Status :: 4 - Beta
Classifier: Intended Audience :: Developers
Classifier: Topic :: Security
Classifier: Programming Language :: Python :: 2.7
Classifier: Programming Language :: Python :: 3.5
Classifier: Programming Language :: Python :: 3.6
Classifier: Programming Language :: Python :: 3.7
Provides-Extra: dev
Provides-Extra: test
Requires-Dist: pexpect; extra == 'test'
Requires-Dist: pytest; extra == 'test'
